pydoxtools/__init__.py
pydoxtools/class_utils.py
pydoxtools/classifier.py
pydoxtools/cluster_utils.py
pydoxtools/dask_operators.py
pydoxtools/document.py
pydoxtools/document_base.py
pydoxtools/extract_classes.py
pydoxtools/extract_filesystem.py
pydoxtools/extract_html.py
pydoxtools/extract_index.py
pydoxtools/extract_nlpchat.py
pydoxtools/extract_objects.py
pydoxtools/extract_ocr.py
pydoxtools/extract_pandoc.py
pydoxtools/extract_spacy.py
pydoxtools/extract_tables.py
pydoxtools/extract_textstructure.py
pydoxtools/file_utils.py
pydoxtools/gui.py
pydoxtools/html_utils.py
pydoxtools/labeling.py
pydoxtools/list_utils.py
pydoxtools/math_utils.py
pydoxtools/models.py
pydoxtools/nlp_utils.py
pydoxtools/ocr_language_mappings.py
pydoxtools/operator_huggingface.py
pydoxtools/operators_base.py
pydoxtools/pdf_utils.py
pydoxtools/random_data_generators.py
pydoxtools/settings.py
pydoxtools/training.py
pydoxtools/visual_document_analysis.py
pydoxtools/visualization.py
pydoxtools/webdav_utils.py
pydoxtools-0.8.0.dist-info/LICENSE
pydoxtools-0.8.0.dist-info/METADATA
pydoxtools-0.8.0.dist-info/WHEEL
pydoxtools-0.8.0.dist-info/entry_points.txt
pydoxtools-0.8.0.dist-info/RECORD
