Metadata-Version: 2.1
Name: pydoxtools
Version: 0.8.0
Summary: This library contains a set of tools in order to extract and synthesize structured information from documents
Home-page: https://pydoxtools.xyntopia.com
License: MIT
Keywords: AI,document-analysis,LLM,NLP,ML
Author: thomas meschede
Author-email: yeusblender@gmail.com
Requires-Python: >=3.8,<4.0
Classifier: License :: OSI Approved :: MIT License
Classifier: Programming Language :: Python :: 3
Classifier: Programming Language :: Python :: 3.8
Classifier: Programming Language :: Python :: 3.9
Classifier: Programming Language :: Python :: 3.10
Classifier: Programming Language :: Python :: 3.11
Classifier: Programming Language :: Python :: 3.12
Provides-Extra: etl
Provides-Extra: inference
Requires-Dist: Pint (>=0.16.1)
Requires-Dist: Shapely (>=1.8.0,<2.0.0)
Requires-Dist: appdirs (>=1.4.4,<2.0.0)
Requires-Dist: beautifulsoup4 (>=4.8.0) ; extra == "etl" or extra == "inference"
Requires-Dist: chardet (>=5.1.0,<6.0.0)
Requires-Dist: dask[complete] (>=2023.4.1,<2024.0.0) ; extra == "etl"
Requires-Dist: diskcache (>=5.6.1,<6.0.0)
Requires-Dist: extruct (>=0.9.0) ; extra == "etl"
Requires-Dist: fastcoref (>=2.1.6,<3.0.0) ; extra == "inference"
Requires-Dist: goose3 (>=3.1.6,<4.0.0) ; extra == "etl"
Requires-Dist: gpt4all (>=1.0.8,<2.0.0) ; extra == "inference"
Requires-Dist: hnswlib (>=0.6.2) ; extra == "etl" or extra == "inference"
Requires-Dist: langdetect (>=1.0.8,<2.0.0) ; extra == "etl"
Requires-Dist: lxml (>=4.6.2)
Requires-Dist: networkx (>=2.8.6,<3.0.0) ; extra == "etl"
Requires-Dist: openai (>=0.27.4,<0.28.0) ; extra == "etl"
Requires-Dist: packaging (>=23.0,<24.0)
Requires-Dist: pandas (>=2.0.1,<3.0.0) ; extra == "etl" or extra == "inference"
Requires-Dist: pandoc (>=2.4b0,<3.0) ; extra == "etl"
Requires-Dist: pdf2image (>=1.16.0,<2.0.0) ; extra == "etl"
Requires-Dist: pdfminer.six (>=20200726) ; extra == "etl"
Requires-Dist: pikepdf (>=2.10.0)
Requires-Dist: pydantic (>=2.0.0,<3.0.0)
Requires-Dist: pydantic-settings (>=2.1.0,<3.0.0)
Requires-Dist: pygraphviz (>=1.11,<2.0) ; extra == "etl"
Requires-Dist: pytesseract (>=0.3.10,<0.4.0) ; extra == "etl"
Requires-Dist: python-magic (>=0.4.27,<0.5.0)
Requires-Dist: python-pptx (>=0.6.21,<0.7.0) ; extra == "etl"
Requires-Dist: pytorch-lightning (>=1.5.6) ; extra == "inference"
Requires-Dist: pyyaml (>=6.0,<7.0)
Requires-Dist: quantities (>=0.12.4) ; extra == "etl"
Requires-Dist: quantulum3 (>=0.7.4) ; extra == "etl"
Requires-Dist: readability-lxml (>=0.8.1,<0.9.0) ; extra == "etl"
Requires-Dist: scikit-learn (>=1.0.2,<2.0.0) ; extra == "inference"
Requires-Dist: spacy (>=3.7.0,<4.0.0) ; extra == "etl" or extra == "inference"
Requires-Dist: stemming (>=1.0.1) ; extra == "etl"
Requires-Dist: tabulate (>=0.9.0,<0.10.0)
Requires-Dist: timm (>=0.9.5,<0.10.0) ; extra == "inference"
Requires-Dist: tldextract (>=2.2.3) ; extra == "etl"
Requires-Dist: torch (>=1.12.1,!=2.0.1) ; extra == "inference"
Requires-Dist: tqdm (>=4.47.0) ; extra == "inference"
Requires-Dist: transformers (>=4.17.0) ; extra == "inference"
Requires-Dist: urlextract (>=1.1.0) ; extra == "etl" or extra == "inference"
Project-URL: Documentation, https://pydoxtools.xyntopia.com
Project-URL: Repository, https://github.com/xyntopia/pydoxtools
